ignacio_test/__init__.py
ignacio_test/example.py
ignacio_test-0.0.9.dist-info/LICENSE
ignacio_test-0.0.9.dist-info/METADATA
ignacio_test-0.0.9.dist-info/WHEEL
ignacio_test-0.0.9.dist-info/top_level.txt
ignacio_test-0.0.9.dist-info/RECORD
